screen/__init__.py
screen/compat.py
screen/old_str_util.py
screen/str_util.so
screen-1.0.0.dist-info/DESCRIPTION.rst
screen-1.0.0.dist-info/METADATA
screen-1.0.0.dist-info/RECORD
screen-1.0.0.dist-info/WHEEL
screen-1.0.0.dist-info/metadata.json
screen-1.0.0.dist-info/top_level.txt
